django_easy_schedule/__init__.py
django_easy_schedule/admin.py
django_easy_schedule/apps.py
django_easy_schedule/models.py
django_easy_schedule/tests.py
django_easy_schedule/views.py
django_easy_schedule/management/__init__.py
django_easy_schedule/management/commands/__init__.py
django_easy_schedule/management/commands/jobs.py
django_easy_schedule/migrations/__init__.py
django_easy_schedule-0.1.7.dist-info/LICENSE
django_easy_schedule-0.1.7.dist-info/METADATA
django_easy_schedule-0.1.7.dist-info/WHEEL
django_easy_schedule-0.1.7.dist-info/top_level.txt
django_easy_schedule-0.1.7.dist-info/RECORD
