Metadata-Version: 2.1
Name: django-easy-schedule
Version: 0.1.7
Summary: Django integration with schedule module
Home-page: https://github.com/waqqas/django-easy-schedule
Author: Waqqas Jabbar
Author-email: waqqas.jabbar@egmail.com
License: MIT
Keywords: django,schedule
Platform: UNKNOWN
Classifier: Development Status :: 4 - Beta
Classifier: Environment :: Web Environment
Classifier: Framework :: Django
Classifier: Intended Audience :: Developers
Classifier: License :: OSI Approved :: MIT License
Classifier: Operating System :: OS Independent
Classifier: Programming Language :: Python
Classifier: Programming Language :: Python :: 3
Classifier: Programming Language :: Python :: 3.9
Classifier: Programming Language :: Python :: 3.10
Classifier: Programming Language :: Python :: 3.11
Requires-Python: >=3.9
License-File: LICENSE
Requires-Dist: Django >=4.0
Requires-Dist: schedule >=1.0
